<?xml version="1.0" encoding="utf-8"?>
<openerp>
    <data>
        <record model="ir.module.category" id="base.module_category_syndic_management">
            <field name="name">Syndic Management</field>
        </record>

        <record id="syndic_client" model="res.groups">
            <field name="name">Syndic/Client</field>
            <field name="category_id" ref="base.module_category_syndic_management"/>
        </record>

        <record id="syndic_employe" model="res.groups">
            <field name="name">Syndic/Employe</field>
            <field name="category_id" ref="base.module_category_syndic_management"/>
            <field name="implied_ids" eval="[(6,0,[ref('syndic_client')])]"/>
        </record>

        <record id="syndic_manager" model="res.groups">
            <field name="name">Syndic/Manager</field>
            <field name="category_id" ref="base.module_category_syndic_management"/>
            <field name="implied_ids" eval="[(6,0,[ref('syndic_client'),ref('syndic_employe')])]"/>
        </record>

        <record id="syndic_calendar_seeall" model="ir.rule">
            <field ref="calendar.model_calendar_event" name="model_id"/>
            <field name="name">All Calendar syndic</field>
            <field name="domain_force">[(1,'=',1)]</field>
            <field name="groups" eval="[(4, ref('syndic_employe'))]"/>
        </record>
    </data>
</openerp>
